scheckbl/__init__.py
scheckbl/check.py
scheckbl/find.py
scheckbl/get.py
scheckbl/similar.py
scheckbl-1.1.0.dist-info/licenses/LICENSE
scheckbl-1.1.0.dist-info/METADATA
scheckbl-1.1.0.dist-info/WHEEL
scheckbl-1.1.0.dist-info/top_level.txt
scheckbl-1.1.0.dist-info/RECORD
