Metadata-Version: 2.4
Name: scheckbl
Version: 1.1.0
Summary: Lightweight Python library for detecting, searching, and analyzing forbidden words and phrases in text data.
Author: Stainowy
License: Copyright 2025 SCheck-Blocklist
Project-URL: Homepage, https://github.com/SCheck-Blocklist/SCheck-Blocklist
Project-URL: Repository, https://github.com/SCheck-Blocklist/Python-Library
Project-URL: Main Website, https://scheck-blocklist.vercel.app
Project-URL: Library Webiste, https://scheck-blocklist.vercel.app/library
Requires-Python: >=3.7
License-File: LICENSE
Dynamic: license-file
